SpatialQuery/__init__.py
SpatialQuery/spatial_query.py
SpatialQuery/spatial_query_multiple_fov.py
SpatialQuery/utils.py
spatialquery-0.0.2.dist-info/licenses/LICENSE
spatialquery-0.0.2.dist-info/METADATA
spatialquery-0.0.2.dist-info/WHEEL
spatialquery-0.0.2.dist-info/top_level.txt
spatialquery-0.0.2.dist-info/RECORD
