Metadata-Version: 2.4
Name: SpatialQuery
Version: 0.0.2
Home-page: https://github.com/ShaokunAn/Spatial-Query
Author: Shaokun An
Author-email: shan12@bwh.harvard.edu
License: MIT
Classifier: Development Status :: 3 - Alpha
Classifier: Intended Audience :: Developers
Classifier: Programming Language :: Python :: 3
Requires-Python: >=3.8
License-File: LICENSE
Requires-Dist: setuptools>=68.0.0
Requires-Dist: anndata>=0.8.0
Requires-Dist: pandas>=2.0.3
Requires-Dist: scipy
Requires-Dist: matplotlib>=3.7.5
Requires-Dist: mlxtend>=0.23.1
Requires-Dist: seaborn>=0.13.2
Requires-Dist: scikit-learn>=1.3.2
Requires-Dist: statsmodels>=0.14.4
Requires-Dist: scanpy>=1.11.1
Dynamic: author
Dynamic: author-email
Dynamic: classifier
Dynamic: description
Dynamic: description-content-type
Dynamic: home-page
Dynamic: license
Dynamic: license-file
Dynamic: requires-dist
Dynamic: requires-python
